lion_orm/__init__.py
lion_orm/connect.py
lion_orm/errors.py
lion_orm/field.py
lion_orm/model.py
lion_orm/objects.py
lion_orm/query.py
lion_orm/query_builder.py
lion_orm/query_set.py
lion_orm-0.1.0.dist-info/METADATA
lion_orm-0.1.0.dist-info/WHEEL
lion_orm-0.1.0.dist-info/top_level.txt
lion_orm-0.1.0.dist-info/RECORD
