Metadata-Version: 2.1
Name: lion-orm
Version: 0.1.0
Summary: Lion ORM - революционная в своей примитивности ОРМ для Sqlite.
Home-page: https://github.com/pomponchik/lion_orm
Author: Evgeniy Blinov
Author-email: zheni-b@yandex.ru
License: UNKNOWN
Platform: UNKNOWN
Classifier: Programming Language :: Python :: 3.8
Classifier: License :: OSI Approved :: GNU General Public License v3 (GPLv3)
